signalhooks/__init__.py
signalhooks/apps.py
signalhooks/hooks.py
signalhooks-0.1.1.dist-info/LICENSE
signalhooks-0.1.1.dist-info/WHEEL
signalhooks-0.1.1.dist-info/METADATA
signalhooks-0.1.1.dist-info/RECORD
