Metadata-Version: 2.1
Name: signalhooks
Version: 0.1.1
Summary: Set of useful hooks that you can attach to your Django Signals to notify other services when a Signal is triggered
Author: Martin Zugnoni
Author-email: martin.zugnoni@gmail.com
Requires-Python: >=3.7,<4
Classifier: Programming Language :: Python :: 3
Classifier: Programming Language :: Python :: 3.7
Classifier: Programming Language :: Python :: 3.8
Requires-Dist: Django (>=2.2)
Requires-Dist: boto3 (>=1.14)
Requires-Dist: requests (>=2.23)
